penguinevaluate/__init__.py
penguinevaluate/app.py
penguinevaluate/constants.py
penguinevaluate/evaluate.py
penguinevaluate/get_snowflake_data.py
penguinevaluate-0.2.1.dist-info/METADATA
penguinevaluate-0.2.1.dist-info/WHEEL
penguinevaluate-0.2.1.dist-info/licence.txt
penguinevaluate-0.2.1.dist-info/top_level.txt
penguinevaluate-0.2.1.dist-info/RECORD
